regex_toolkit/__init__.py
regex_toolkit/base.py
regex_toolkit/constants.py
regex_toolkit/enums.py
regex_toolkit/utils.py
regex_toolkit-0.1.0.dist-info/LICENSE
regex_toolkit-0.1.0.dist-info/METADATA
regex_toolkit-0.1.0.dist-info/WHEEL
regex_toolkit-0.1.0.dist-info/top_level.txt
regex_toolkit-0.1.0.dist-info/RECORD
