Metadata-Version: 2.1
Name: regex_toolkit
Version: 0.1.0
Summary: Tools for creating RE and RE2 expressions
Author-email: The Phosmic Development Team <dev@phosmic.com>
License: GNU GENERAL PUBLIC LICENSE
Project-URL: homepage, https://pypi.org/project/regex-toolkit/
Project-URL: repository, https://github.com/Phosmic/regex-toolkit
Project-URL: issues, https://github.com/Phosmic/regex-toolkit/issues
Keywords: re,re2,regex,expression,pattern,tool,toolkit
Classifier: Development Status :: 3 - Alpha
Classifier: Intended Audience :: Developers
Classifier: License :: OSI Approved :: GNU General Public License v3 or later (GPLv3+)
Classifier: Natural Language :: English
Classifier: Operating System :: OS Independent
Classifier: Programming Language :: Python
Classifier: Programming Language :: Python :: 3
Classifier: Programming Language :: Python :: 3 :: Only
Classifier: Programming Language :: Python :: 3.10
Classifier: Programming Language :: Python :: 3.11
Classifier: Programming Language :: Python :: 3.12
Classifier: Topic :: Utilities
Classifier: Topic :: Software Development
Classifier: Topic :: Software Development :: Libraries
Classifier: Topic :: Software Development :: Libraries :: Python Modules
Requires-Python: <4,>=3.10
License-File: LICENSE
